DjangoZhigeJianyiBokeDajianJiaocheng/README.md
DjangoZhigeJianyiBokeDajianJiaocheng/__init__.py
DjangoZhigeJianyiBokeDajianJiaocheng/__main__.py
DjangoZhigeJianyiBokeDajianJiaocheng/file.epub
DjangoZhigeJianyiBokeDajianJiaocheng/index.html
DjangoZhigeJianyiBokeDajianJiaocheng/css/__init__.py
DjangoZhigeJianyiBokeDajianJiaocheng/css/annotations.css
DjangoZhigeJianyiBokeDajianJiaocheng/css/main.css
DjangoZhigeJianyiBokeDajianJiaocheng/css/normalize.css
DjangoZhigeJianyiBokeDajianJiaocheng/css/popup.css
DjangoZhigeJianyiBokeDajianJiaocheng/font/__init__.py
DjangoZhigeJianyiBokeDajianJiaocheng/font/fontello.eot
DjangoZhigeJianyiBokeDajianJiaocheng/font/fontello.svg
DjangoZhigeJianyiBokeDajianJiaocheng/font/fontello.ttf
DjangoZhigeJianyiBokeDajianJiaocheng/font/fontello.woff
DjangoZhigeJianyiBokeDajianJiaocheng/img/__init__.py
DjangoZhigeJianyiBokeDajianJiaocheng/img/annotator-glyph-sprite.png
DjangoZhigeJianyiBokeDajianJiaocheng/img/annotator-icon-sprite.png
DjangoZhigeJianyiBokeDajianJiaocheng/img/apple-touch-icon.png
DjangoZhigeJianyiBokeDajianJiaocheng/img/cancelfullscreen.png
DjangoZhigeJianyiBokeDajianJiaocheng/img/close.png
DjangoZhigeJianyiBokeDajianJiaocheng/img/fullscreen.png
DjangoZhigeJianyiBokeDajianJiaocheng/img/loader.gif
DjangoZhigeJianyiBokeDajianJiaocheng/img/menu-icon.png
DjangoZhigeJianyiBokeDajianJiaocheng/img/save.png
DjangoZhigeJianyiBokeDajianJiaocheng/img/saved.png
DjangoZhigeJianyiBokeDajianJiaocheng/img/settings-s.png
DjangoZhigeJianyiBokeDajianJiaocheng/img/settings.png
DjangoZhigeJianyiBokeDajianJiaocheng/img/star.png
DjangoZhigeJianyiBokeDajianJiaocheng/js/__init__.py
DjangoZhigeJianyiBokeDajianJiaocheng/js/epub.js
DjangoZhigeJianyiBokeDajianJiaocheng/js/epub.min.js
DjangoZhigeJianyiBokeDajianJiaocheng/js/epub.min.map
DjangoZhigeJianyiBokeDajianJiaocheng/js/hooks.min.js
DjangoZhigeJianyiBokeDajianJiaocheng/js/hooks.min.map
DjangoZhigeJianyiBokeDajianJiaocheng/js/reader.js
DjangoZhigeJianyiBokeDajianJiaocheng/js/reader.js.map
django_zhige_jianyi_boke_dajian_jiaocheng-2024.3.1.0.dist-info/METADATA
django_zhige_jianyi_boke_dajian_jiaocheng-2024.3.1.0.dist-info/WHEEL
django_zhige_jianyi_boke_dajian_jiaocheng-2024.3.1.0.dist-info/entry_points.txt
django_zhige_jianyi_boke_dajian_jiaocheng-2024.3.1.0.dist-info/top_level.txt
django_zhige_jianyi_boke_dajian_jiaocheng-2024.3.1.0.dist-info/RECORD
